README.txt
TGExtJS.kpf
setup.py
TGExtJS/__init__.py
TGExtJS/release.py
TGExtJS/widgets.py
TGExtJS.egg-info/PKG-INFO
TGExtJS.egg-info/SOURCES.txt
TGExtJS.egg-info/dependency_links.txt
TGExtJS.egg-info/entry_points.txt
TGExtJS.egg-info/not-zip-safe
TGExtJS.egg-info/paster_plugins.txt
TGExtJS.egg-info/requires.txt
TGExtJS.egg-info/sqlobject.txt
TGExtJS.egg-info/top_level.txt
TGExtJS/static/ext-all.js
TGExtJS/static/license.txt
TGExtJS/static/thirdparty.js
TGExtJS/static/adapter/ext/ext-base.js
TGExtJS/static/adapter/prototype/ext-prototype-adapter.js
TGExtJS/static/package/color-palette.js
TGExtJS/static/package/date.js
TGExtJS/static/package/resizable.js
TGExtJS/static/package/splitbar.js
TGExtJS/static/package/util.js
TGExtJS/static/package/widget-core.js
TGExtJS/static/package/button/button.js
TGExtJS/static/package/data/data.js
TGExtJS/static/package/datepicker/datepicker.js
TGExtJS/static/package/dialog/dialogs.js
TGExtJS/static/package/dragdrop/dragdrop.js
TGExtJS/static/package/form/form.js
TGExtJS/static/package/grid/edit-grid.js
TGExtJS/static/package/grid/grid.js
TGExtJS/static/package/layout/layout.js
TGExtJS/static/package/menu/menus.js
TGExtJS/static/package/qtips/qtips.js
TGExtJS/static/package/tabs/tabs.js
TGExtJS/static/package/toolbar/toolbar.js
TGExtJS/static/package/tree/tree.js
TGExtJS/static/resources/css/basic-dialog.css
TGExtJS/static/resources/css/box.css
TGExtJS/static/resources/css/button.css
TGExtJS/static/resources/css/combo.css
TGExtJS/static/resources/css/core.css
TGExtJS/static/resources/css/date-picker.css
TGExtJS/static/resources/css/dd.css
TGExtJS/static/resources/css/debug.css
TGExtJS/static/resources/css/editor.css
TGExtJS/static/resources/css/ext-all.css
TGExtJS/static/resources/css/form.css
TGExtJS/static/resources/css/grid.css
TGExtJS/static/resources/css/layout.css
TGExtJS/static/resources/css/menu.css
TGExtJS/static/resources/css/qtips.css
TGExtJS/static/resources/css/reset-min.css
TGExtJS/static/resources/css/resizable.css
TGExtJS/static/resources/css/tabs.css
TGExtJS/static/resources/css/toolbar.css
TGExtJS/static/resources/css/tree.css
TGExtJS/static/resources/css/xtheme-aero.css
TGExtJS/static/resources/css/xtheme-gray.css
