Metadata-Version: 1.0
Name: TGExtJS
Version: 0.2.3
Summary: ExtJS packaged as collection of TurboGears widgets.
Home-page: UNKNOWN
Author: W-Mark Kubacki
Author-email: wmark.tgextjs@hurrikane.de
License: LGPL
Keywords: turbogears.widgets
Platform: UNKNOWN
Classifier: Development Status :: 2 - Pre-Alpha
Classifier: Operating System :: OS Independent
Classifier: Programming Language :: Python
Classifier: Programming Language :: JavaScript
Classifier: Topic :: Software Development :: Libraries :: Python Modules
Classifier: Framework :: TurboGears
Classifier: Framework :: TurboGears :: Widgets
Classifier: License :: OSI Approved :: GNU Library or Lesser General Public License (LGPL)
